deli/__init__.py
deli/cache/__init__.py
deli/cache/client.py
deli/counter/__init__.py
deli/counter/settings.py
deli/counter/auth/__init__.py
deli/counter/auth/permission.py
deli/counter/auth/token.py
deli/counter/cli/__init__.py
deli/counter/cli/app.py
deli/counter/cli/main.py
deli/counter/cli/commands/__init__.py
deli/counter/cli/commands/gen_admin.py
deli/counter/http/__init__.py
deli/counter/http/app.py
deli/counter/http/router.py
deli/counter/http/wsgi.py
deli/counter/http/mounts/__init__.py
deli/counter/http/mounts/root/__init__.py
deli/counter/http/mounts/root/mount.py
deli/counter/http/mounts/root/errors/__init__.py
deli/counter/http/mounts/root/errors/quota.py
deli/counter/http/mounts/root/routes/__init__.py
deli/counter/http/mounts/root/routes/health.py
deli/counter/http/mounts/root/routes/swagger.py
deli/counter/http/mounts/root/routes/auth/__init__.py
deli/counter/http/mounts/root/routes/auth/v1/__init__.py
deli/counter/http/mounts/root/routes/auth/v1/oauth.py
deli/counter/http/mounts/root/routes/auth/v1/validation_models/__init__.py
deli/counter/http/mounts/root/routes/auth/v1/validation_models/oauth.py
deli/counter/http/mounts/root/routes/compute/__init__.py
deli/counter/http/mounts/root/routes/compute/v1/__init__.py
deli/counter/http/mounts/root/routes/compute/v1/flavor.py
deli/counter/http/mounts/root/routes/compute/v1/images.py
deli/counter/http/mounts/root/routes/compute/v1/instance.py
deli/counter/http/mounts/root/routes/compute/v1/keypairs.py
deli/counter/http/mounts/root/routes/compute/v1/network_ports.py
deli/counter/http/mounts/root/routes/compute/v1/networks.py
deli/counter/http/mounts/root/routes/compute/v1/volume.py
deli/counter/http/mounts/root/routes/compute/v1/validation_models/__init__.py
deli/counter/http/mounts/root/routes/compute/v1/validation_models/flavor.py
deli/counter/http/mounts/root/routes/compute/v1/validation_models/images.py
sandwichcloud_deli-0.0.39.dist-info/METADATA
sandwichcloud_deli-0.0.39.dist-info/RECORD
sandwichcloud_deli-0.0.39.dist-info/WHEEL
sandwichcloud_deli-0.0.39.dist-info/entry_points.txt
sandwichcloud_deli-0.0.39.dist-info/pbr.json
sandwichcloud_deli-0.0.39.dist-info/top_level.txt
