Metadata-Version: 2.1
Name: sandwichcloud-deli
Version: 0.0.39
Summary: API, Metadata and Controller for Sandwich Cloud
Home-page: https://github.com/sandwichcloud/deli
Author: Ryan Belgrave
Author-email: rmb1993@gmail.com
License: MIT
Platform: UNKNOWN
Classifier: Development Status :: 3 - Alpha
Classifier: Environment :: Web Environment
Classifier: Intended Audience :: Developers
Classifier: License :: OSI Approved :: MIT License
Classifier: Operating System :: OS Independent
Classifier: Programming Language :: Python
Classifier: Topic :: Internet :: WWW/HTTP :: WSGI :: Application
Requires-Dist: clify (==0.0.3)
Requires-Dist: pbr (==4.0.3)
Requires-Dist: python-dotenv (==0.7.1)
Requires-Dist: go-defer (==1.0.1)
Requires-Dist: kubernetes (==4.0.0)
Requires-Dist: cherrypy (==13.1.0)
Requires-Dist: Routes (==2.4.1)
Requires-Dist: schematics (==2.0.1)
Requires-Dist: simple-settings (==0.12.0)
Requires-Dist: arrow (==0.10.0)
Requires-Dist: pyvmomi (==6.5.0.2017.5-1)
Requires-Dist: cryptography (==2.1.4)
Requires-Dist: passlib (==1.7.1)
Requires-Dist: bcrypt (==3.1.4)
Requires-Dist: pygithub (==1.35)
Requires-Dist: redis (==2.10.6)
Requires-Dist: requests (==2.19.1)
Requires-Dist: python-jose (==3.0.0)
Requires-Dist: apispec (==0.38.0)
Requires-Dist: pyk8s-controller (==0.0.7)
Requires-Dist: ingredients.http (==0.0.17)
Requires-Dist: vmw-cloudinit-metadata (==0.0.8)
